viur/shop/__init__.py
viur/shop/globals.py
viur/shop/shop.py
viur/shop/version.py
viur/shop/data/translations.py
viur/shop/data/zip_patterns.py
viur/shop/modules/__init__.py
viur/shop/modules/abstract.py
viur/shop/modules/address.py
viur/shop/modules/api.py
viur/shop/modules/cart.py
viur/shop/modules/discount.py
viur/shop/modules/discount_condition.py
viur/shop/modules/order.py
viur/shop/modules/shipping.py
viur/shop/modules/shipping_config.py
viur/shop/modules/vat_rate.py
viur/shop/payment_providers/__init__.py
viur/shop/payment_providers/abstract.py
viur/shop/payment_providers/amazon_pay.py
viur/shop/payment_providers/invoice.py
viur/shop/payment_providers/paypal_checkout.py
viur/shop/payment_providers/prepayment.py
viur/shop/payment_providers/unzer_abstract.py
viur/shop/payment_providers/unzer_applepay.py
viur/shop/payment_providers/unzer_bancontact.py
viur/shop/payment_providers/unzer_card.py
viur/shop/payment_providers/unzer_googlepay.py
viur/shop/payment_providers/unzer_ideal.py
viur/shop/payment_providers/unzer_paylater_invoice.py
viur/shop/payment_providers/unzer_paypal.py
viur/shop/payment_providers/unzer_sofort.py
viur/shop/services/__init__.py
viur/shop/services/events.py
viur/shop/services/hooks.py
viur/shop/skeletons/__init__.py
viur/shop/skeletons/address.py
viur/shop/skeletons/article.py
viur/shop/skeletons/cart.py
viur/shop/skeletons/discount.py
viur/shop/skeletons/discount_condition.py
viur/shop/skeletons/order.py
viur/shop/skeletons/shipping.py
viur/shop/skeletons/shipping_config.py
viur/shop/skeletons/shipping_precondition.py
viur/shop/skeletons/vat.py
viur/shop/skeletons/vat_rate.py
viur/shop/types/__init__.py
viur/shop/types/data.py
viur/shop/types/dc_scope.py
viur/shop/types/enums.py
viur/shop/types/error.py
viur/shop/types/exceptions.py
viur/shop/types/price.py
viur/shop/types/response.py
viur/shop/types/results.py
viur/shop/types/typed_dicts.py
viur/shop/types_global/__init__.py
viur/shop/types_global/global_var.py
viur_shop-0.13.2.dist-info/licenses/LICENSE
viur_shop-0.13.2.dist-info/METADATA
viur_shop-0.13.2.dist-info/WHEEL
viur_shop-0.13.2.dist-info/top_level.txt
viur_shop-0.13.2.dist-info/RECORD
