Metadata-Version: 2.4
Name: viur-shop
Version: 0.13.2
Summary: A modular e-commerce extension for the ViUR framework
Author-email: Sven Eberth <se@mausbrand.de>
Maintainer-email: Sven Eberth <se@mausbrand.de>
License: MIT License
Project-URL: Documentation, https://viur-shop.readthedocs.io
Project-URL: Repository, https://github.com/viur-framework/viur-shop.git
Project-URL: Bug Tracker, https://github.com/viur-framework/viur-shop/issues
Project-URL: Changelog, https://github.com/viur-framework/viur-shop/releases
Keywords: viur,plugin,backend,shop,ecommerce
Classifier: Development Status :: 4 - Beta
Classifier: Intended Audience :: Developers
Classifier: License :: OSI Approved :: MIT License
Classifier: Operating System :: OS Independent
Classifier: Programming Language :: Python :: 3.11
Classifier: Programming Language :: Python :: 3.12
Classifier: Programming Language :: Python :: 3.13
Classifier: Topic :: Software Development :: Libraries :: Python Modules
Requires-Python: >=3.11
License-File: LICENSE
Requires-Dist: viur-toolkit>=0.2.0
Requires-Dist: viur-core>=3.7.0
Requires-Dist: cachetools>=5.0
Provides-Extra: unzer
Requires-Dist: unzer~=1.3; extra == "unzer"
Provides-Extra: paypal
Requires-Dist: paypal-server-sdk~=1.0; extra == "paypal"
Dynamic: license-file
